tradovate/__init__.py
tradovate/__version__.py
tradovate/accounting.py
tradovate/alerts.py
tradovate/client.py
tradovate/config.py
tradovate/configuration.py
tradovate/contractLibrary.py
tradovate/exceptions.py
tradovate/orders.py
tradovate/positions.py
tradovate/risks.py
tradovate/session.py
tradovate/stream.py
tradovate/tdws.py
tradovate/users.py
tradovate/auth/__init__.py
tradovate/auth/__main__.py
tradovate-0.0.1.dist-info/LICENSE
tradovate-0.0.1.dist-info/METADATA
tradovate-0.0.1.dist-info/WHEEL
tradovate-0.0.1.dist-info/top_level.txt
tradovate-0.0.1.dist-info/RECORD
