Metadata-Version: 2.1
Name: tradovate
Version: 0.0.1
Summary: The package fetch data from tradovate.
Home-page: https://github.com/dearvn/tradovate
Author: Donald
Author-email: donald.nguyen.it@gmail.com
License: MIT
Project-URL: Bug Tracker, https://github.com/dearvn/tradovate/issues
Platform: UNKNOWN
Classifier: License :: OSI Approved :: MIT License
Classifier: Programming Language :: Python
Classifier: Programming Language :: Python :: 3
Classifier: Programming Language :: Python :: 3.6
Classifier: Programming Language :: Python :: Implementation :: CPython
Classifier: Programming Language :: Python :: Implementation :: PyPy
Requires-Python: >=3.6.0
License-File: LICENSE
Requires-Dist: redis
Requires-Dist: pytz
Requires-Dist: requests
Requires-Dist: websocket-client
